{"IconTweaker":{"id":"IconTweaker","name":"Icon Tweaker","description":"Tab icon resizer for Essentials, Pinned, Normal and Workspaces.","homepage":"https://github.com/allecsc/Icon-Tweaker","preferences":"preferences.json","style":"chrome.css","readme":"https://raw.githubusercontent.com/allecsc/Icon-Tweaker/refs/heads/main/README.md","image":"https://raw.githubusercontent.com/allecsc/Icon-Tweaker/refs/heads/main/image.png","author":"celalalt","version":"1.2","tags":["sine","tabs","icons","customization","resize"],"createdAt":"2025-05-31","updatedAt":"2025-06-16","fork":["zen","firefox"],"editable-files":["preferences.json","readme.md","chrome.css"],"no-updates":true,"enabled":false},"42b8c4ac-76d5-4521-9917-2e478931ee53":{"updatedAt":"2025-11-12T15:04:50Z","id":"42b8c4ac-76d5-4521-9917-2e478931ee53","homepage":"https://github.com/rasyidrafi/zen-compact-transparent-mode","name":"Zen Compact Transparent Mode","description":"Make popups UI menu transparent with custom settings.","version":"2.0.0","style":{"chrome":"chrome.css","content":""},"preferences":"preferences.json","no-updates":false,"enabled":true},"ae7868dc-1fa1-469e-8b89-a5edf7ab1f24":{"updatedAt":"2026-04-11T07:33:58Z","id":"ae7868dc-1fa1-469e-8b89-a5edf7ab1f24","homepage":"https://github.com/Tanay-Kar/Zen-Themes","name":"Load Bar","description":"Creates a sleek loading bar and mute status for single toolbar mode.","version":"1.0.0","style":{"chrome":"","content":""},"preferences":"","no-updates":false,"enabled":true},"ad97bb70-0066-4e42-9b5f-173a5e42c6fc":{"id":"ad97bb70-0066-4e42-9b5f-173a5e42c6fc","name":"SuperPins","description":"This Zen Mod enhances pinned tabs/Essentials, by making some UI/UX changes.","homepage":"https://github.com/CosmoCreeper/Zen-Themes/tree/main/SuperPins","style":{"chrome":"chrome.css","content":""},"readme":"https://raw.githubusercontent.com/zen-browser/theme-store/main/themes/ad97bb70-0066-4e42-9b5f-173a5e42c6fc/readme.md","image":"https://raw.githubusercontent.com/zen-browser/theme-store/main/themes/ad97bb70-0066-4e42-9b5f-173a5e42c6fc/image.png","author":"CosmoCreeper","version":"1.7.2","preferences":"preferences.json","tags":["tabs"],"createdAt":"2024-08-28","updatedAt":"2026-04-09","fork":["zen"],"no-updates":false,"enabled":true},"d8b79d4a-6cba-4495-9ff6-d6d30b0e94fe":{"updatedAt":"2025-07-23T12:41:35Z","id":"d8b79d4a-6cba-4495-9ff6-d6d30b0e94fe","homepage":"https://github.com/HliasOuzounis/zen-browser-better-active-tab-indicator","description":"Adds a bright line next to the active tab to better highlight it.","createdAt":"2024-09-04T16:35:38Z","name":"Better Active Tab","version":"1.0.3","style":"chrome.css","readme":"https://raw.githubusercontent.com/zen-browser/theme-store/main/themes/d8b79d4a-6cba-4495-9ff6-d6d30b0e94fe/readme.md","image":"https://raw.githubusercontent.com/zen-browser/theme-store/main/themes/d8b79d4a-6cba-4495-9ff6-d6d30b0e94fe/image.png","editable-files":["readme.md","chrome.css"],"no-updates":false,"enabled":true,"preferences":""},"72f8f48d-86b9-4487-acea-eb4977b18f21":{"updatedAt":"2025-10-28T16:26:28Z","id":"72f8f48d-86b9-4487-acea-eb4977b18f21","homepage":"https://github.com/psu/zen-mods","description":"Re-style and add customization options for the CtrlTab panel.","createdAt":"2025-03-28T07:43:12Z","readme":"https://raw.githubusercontent.com/psu/zen-mods/main/README.md","name":"Better CtrlTab Panel","version":"1.0.1","style":"chrome.css","preferences":"preferences.json","image":"https://raw.githubusercontent.com/zen-browser/theme-store/main/themes/72f8f48d-86b9-4487-acea-eb4977b18f21/image.png","editable-files":["preferences.json","readme.md","chrome.css"],"no-updates":false,"enabled":true},"74c755b3-41a5-4f78-83cb-cd1e1e076bb6":{"id":"74c755b3-41a5-4f78-83cb-cd1e1e076bb6","name":"Better UniExtBtn","description":"change unified extensions button to zen browser icon","homepage":"","style":"chrome.css","readme":"https://raw.githubusercontent.com/zen-browser/theme-store/main/themes/74c755b3-41a5-4f78-83cb-cd1e1e076bb6/readme.md","image":"https://raw.githubusercontent.com/zen-browser/theme-store/main/themes/74c755b3-41a5-4f78-83cb-cd1e1e076bb6/image.png","preferences":"preferences.json","author":"lindongbin","version":"1.0.1","tags":[],"createdAt":"2024-08-30","updatedAt":"2025-01-26","enabled":false},"87196c08-8ca1-4848-b13b-7ea41ee830e7":{"updatedAt":"2025-11-03T00:47:43Z","id":"87196c08-8ca1-4848-b13b-7ea41ee830e7","homepage":"https://github.com/Kaedriz/ZenMods","description":"Enhanced tab preview, respecting user background color and padding","createdAt":"2024-12-06T13:56:19Z","style":{"chrome":"userChrome.css"},"readme":"https://raw.githubusercontent.com/Kaedriz/ZenMods/main/readme.md","name":"Tab Preview Enhanced","version":"aie_1.3.1","preferences":"preferences.json","image":"https://raw.githubusercontent.com/zen-browser/theme-store/main/themes/87196c08-8ca1-4848-b13b-7ea41ee830e7/image.png","editable-files":["preferences.json","readme.md","chrome.css","userChrome.css",{"directory":"CustomizationViewEnhanced","contents":["CustomizationViewEnhanced.css"]},{"directory":"ExtensionMenuEnhanced","contents":["ExtensionMenuEnhanced.css"]},{"directory":"TabPreviewEnhanced","contents":["TabPreviewEnhanced.css"]},{"directory":"src","contents":[".temp.css"]},{"directory":"AudioIndicatorEnhanced","contents":["AudioIndicatorEnhanced.css"]},{"directory":"StatusBarEnhanced","contents":["StatusBarEnhanced.css"]},{"directory":"ContextMenuEnhanced","contents":["ContextMenuEnhanced.css",{"directory":"States","contents":["Page.css"]}]}],"no-updates":false,"enabled":true},"f50841b2-5e4a-4534-985d-b7f7b96088c2":{"updatedAt":"2025-05-10T00:52:08Z","id":"f50841b2-5e4a-4534-985d-b7f7b96088c2","homepage":"https://github.com/JtdeGraaf/zen-remove-split-view-tab-highlight","description":"Removes the border highlight around the active tab while using split view.","createdAt":"2024-10-02T11:52:18Z","name":"NoHighlightSplit","readme":"https://raw.githubusercontent.com/JtdeGraaf/zen-remove-split-view-tab-highlight/main/README.md","version":"1.1.0","style":"chrome.css","image":"https://raw.githubusercontent.com/zen-browser/theme-store/main/themes/f50841b2-5e4a-4534-985d-b7f7b96088c2/image.png","editable-files":["readme.md","chrome.css"],"no-updates":false,"enabled":true,"preferences":""},"f4866f39-cfd6-4498-ab92-54213b8279dc":{"id":"f4866f39-cfd6-4498-ab92-54213b8279dc","name":"Animations Plus","description":"A nice animation pack for Zen Browser.","homepage":"https://github.com/Anoms12/Animations-plus","style":"chrome.css","readme":"https://raw.githubusercontent.com/Anoms12/Animations-plus/main/README.md","image":"https://raw.githubusercontent.com/Anoms12/Animations-plus/main/image.png","author":"Anoms12","version":"1.2.2","tags":["sine","Animations","Anoms12"],"createdAt":"2025-05-20","updatedAt":"2025-06-13","fork":["zen","floorp"],"editable-files":["readme.md","chrome.css"],"no-updates":false,"enabled":false,"preferences":""},"7d577b21-4685-4db2-bb17-d39d08eec199":{"id":"7d577b21-4685-4db2-bb17-d39d08eec199","name":"Bleeding Corners Fix","description":"Fixes the white outlines (or artifacts) on the rounded corners that can appear on some pages. May cause higher GPU usage on some devices.","homepage":"https://github.com/rsiebertdev/zen-themes/tree/main/bleeding-corners-fix","style":"chrome.css","readme":"https://raw.githubusercontent.com/zen-browser/theme-store/main/themes/7d577b21-4685-4db2-bb17-d39d08eec199/readme.md","image":"https://raw.githubusercontent.com/zen-browser/theme-store/main/themes/7d577b21-4685-4db2-bb17-d39d08eec199/image.png","author":"rsiebertdev","version":"1.0.6","tags":[],"createdAt":"2025-02-17","updatedAt":"2025-07-27","enabled":true,"preferences":""},"Neo-Zen":{"id":"Neo-Zen","homepage":"https://github.com/JustVibingWhileCoding/Neo-Zen","author":"JustVibingWhileCoding","name":"Neo Zen","description":"A sleek, futuristic theme for Zen Browser that blends modern design with mindful simplicity","version":"2.1.0","createdAt":"2025-05-31","updatedAt":"2025-12-15","style":{"chrome":"userChrome.css","content":"userContent.css"},"preferences":"preferences.json","readme":"https://raw.githubusercontent.com/JustVibingWhileCoding/Neo-Zen/main/README.md","image":"https://github.com/user-attachments/assets/c37e9f4e-1ab1-43ec-945e-2be1592351a4","tags":["content","chrome","minimal","futuristic"],"fork":["zen"],"no-updates":false,"enabled":true},"vizen-floaty-ui":{"id":"vizen-floaty-ui","name":"Floaty UI","description":"Compact Mode, but it floats. Supports Zen Color Picker and background blur.","homepage":"https://github.com/moktavizen/floaty-ui","readme":"https://raw.githubusercontent.com/moktavizen/floaty-ui/refs/heads/main/README.md","image":"https://raw.githubusercontent.com/moktavizen/floaty-ui/refs/heads/main/media/preview-store.png","style":"chrome.css","preferences":"preferences.json","author":"moktavizen","version":"1.0.2","tags":["compact","compact mode","float"],"createdAt":"2025-06-29","updatedAt":"2025-06-29","fork":["zen"],"editable-files":["preferences.json","readme.md","chrome.css"],"no-updates":false,"enabled":true},"No-Gaps":{"id":"No-Gaps","homepage":"https://github.com/Comp-Tech-Guy/No-Gaps","author":"CompTechGuy","name":"No-Gaps","description":"There will be no gaps in the sides to have a sleek look for every layout","version":"2.5.1","style":{"chrome":"userChrome.css"},"readme":"https://raw.githubusercontent.com/Comp-Tech-Guy/No-Gaps/refs/heads/main/README.md","image":"https://github.com/Comp-Tech-Guy/No-Gaps/blob/main/images/CompactMode.png?raw=true","tags":["Remove","Clean","No-Gaps","Border removed","Border","no-gap","no gap","Minimal","Neat"],"fork":["zen"],"updatedAt":"2025-11-07T16:31:25Z","createdAt":"2025-10-06T18:54:02Z","preferences":"preferences.json","editable-files":["preferences.json","readme.md","chrome.css","userChrome.css"],"no-updates":false,"enabled":true},"3c8ebf69-1042-49b1-8f08-9178f9490659":{"id":"3c8ebf69-1042-49b1-8f08-9178f9490659","name":"Better Music Bar","description":"Make your zen music bar better.","homepage":"https://github.com/rasyidrafi/zen-always-show-music-bar","image":"https://github.com/rasyidrafi/zen-always-show-music-bar/blob/main/image.png?raw=true","style":{"chrome":"userChrome.css"},"readme":"https://raw.githubusercontent.com/rasyidrafi/zen-always-show-music-bar/refs/heads/main/README.md","preferences":"preferences.json","author":"rasyidrafi","version":"1.0.4","tags":["UI"],"createdAt":"2025-07-29","updatedAt":"2025-08-04","fork":["zen","firefox"],"editable-files":["preferences.json","readme.md","chrome.css","userChrome.css"],"no-updates":false,"enabled":true},"e9dae25b-2ddd-4245-8581-a6dcf6d35b82":{"id":"e9dae25b-2ddd-4245-8581-a6dcf6d35b82","name":"Zen Custom URL Bar","description":"Customizable URL bar with animations.","homepage":"https://github.com/rasyidrafi/zen-custom-urlbar","image":"https://github.com/rasyidrafi/zen-custom-urlbar/blob/main/image.png?raw=true","style":{"chrome":"chrome.css","content":""},"readme":"https://raw.githubusercontent.com/rasyidrafi/zen-custom-urlbar/refs/heads/main/README.md","preferences":"preferences.json","author":"rasyidrafi","version":"2.0.3","tags":["Animation","UI"],"createdAt":"2025-07-29","updatedAt":"2025-11-13","fork":["zen","firefox"],"stars":2,"origin":"store","no-updates":false,"enabled":true},"floating-statusbar":{"id":"floating-statusbar","homepage":"https://github.com/qumeqa/floating-statusbar","author":"qumeqa","name":"Floating Statusbar","description":"A floating statusbar for Zen","version":"1.0","style":{"chrome":"userChrome.css","content":""},"readme":"https://raw.githubusercontent.com/qumeqa/floating-statusbar/refs/heads/main/README.md","image":"https://raw.githubusercontent.com/qumeqa/floating-statusbar/refs/heads/main/cover.png","tags":["Float","Floating","Statusbar"],"fork":["zen"],"stars":0,"origin":"store","preferences":"","no-updates":false,"enabled":false},"floating-sidebar":{"id":"floating-sidebar","homepage":"https://github.com/Vertex-Mods/Floating-Sidebar","name":"Floating Sidebar","description":"Lightweight script to, make firefox Sidebar Floating also option to pin/unpin the sidebar.","author":"Bibek Bhusal","version":"1.1.2","updatedAt":"2026-01-24","tags":["Sidebar","Pin"],"preferences":"preferences.json","style":{"chrome":"style.css","content":""},"scripts":{"floating-sidebar.uc.js":{"include":["chrome://browser/content/browser.xhtml"]}},"readme":"https://raw.githubusercontent.com/Vertex-Mods/Floating-Sidebar/main/README.md","createdAt":"2025-06-23","stars":1,"origin":"store","no-updates":false,"enabled":false},"zen-auto-expand-sidebar":{"id":"zen-auto-expand-sidebar","name":"Sidebar Expand on Hover","description":"Expand the sidebar on hover, with many configurations avaliable","homepage":"https://github.com/StormAnon/zen-sidebar-expand-on-hover/tree/sine","style":{"chrome":"chrome.css","content":""},"readme":"https://raw.githubusercontent.com/StormAnon/zen-sidebar-expand-on-hover/sine/README.md","image":"https://raw.githubusercontent.com/StormAnon/zen-sidebar-expand-on-hover/sine/image.png","author":"StormAnon","version":"1.0.0","fork":["zen"],"tags":["ui","customization"],"stars":6,"origin":"store","preferences":"preferences.json","no-updates":false,"enabled":true},"nova":{"id":"nova","homepage":"https://github.com/qumeqa/nova","author":"qumeqa","name":"Nova UI","description":"A Zen theme enhancement that refines spacing, padding, and visual consistency across the interface","version":"2.2","createdAt":"2026-01-30","updatedAt":"2026-02-19","style":{"chrome":"userChrome.css","content":""},"preferences":"preferences.json","readme":"https://raw.githubusercontent.com/qumeqa/nova/refs/heads/main/README.md","image":"https://raw.githubusercontent.com/qumeqa/nova/refs/heads/main/img/cover.jpg","tags":["modern","ui","theme","visual","enhancements","styling","minimal","clean","statusbar","popup","panel","custom font"],"fork":["zen"],"stars":5,"origin":"store","no-updates":false,"enabled":true}}